toolstack/core/exceptions.py
toolstack/core/plugins/__init__.py
toolstack/core/tools.py
toolstack/core/utils.py
toolstack_core-0.1.1.dist-info/WHEEL
toolstack_core-0.1.1.dist-info/METADATA
toolstack_core-0.1.1.dist-info/RECORD
