Metadata-Version: 2.1
Name: toolstack-core
Version: 0.1.1
Summary: 
Author: Pascal Prins
Author-email: pascal.prins@toolstack.ninja
Requires-Python: >=3.9,<4.0
Classifier: Programming Language :: Python :: 3
Classifier: Programming Language :: Python :: 3.10
Classifier: Programming Language :: Python :: 3.9
Requires-Dist: PyYAML (>=5.4.1,<6.0.0)
Requires-Dist: beautifulsoup4 (>=4.10.0,<5.0.0)
Requires-Dist: click (>=8.0.4,<9.0.0)
Requires-Dist: requests (>=2.27.1,<3.0.0)
